{
  "naruto": {
    "ninjutsu": 4,
    "taijutsu": 3.5,
    "genjutsu": 2,
    "intelligence": 3,
    "strength": 3.5,
    "speed": 3.5,
    "stamina": 5,
    "hand_seals": 1.5,
    "total": 26,
    "notes": "OP, absolute legend, better than Sakura"
  },
  "sakura": {
    "ninjutsu": 3,
    "taijutsu": 3,
    "genjutsu": 3.5,
    "intelligence": 4,
    "strength": 3,
    "speed": 3,
    "stamina": 2.5,
    "hand_seals": 4,
    "total": 26,
    "notes": "What is there to describe?"
  },
  "sasuke": {
    "ninjutsu": 5,
    "taijutsu": 3.5,
    "genjutsu": 4,
    "intelligence": 3.5,
    "strength": 3.5,
    "speed": 4.5,
    "stamina": 3.5,
    "hand_seals": 4,
    "total": 31.5,
    "notes": "Orders of magnitude more powerful than Sakura's crying power"
  },
  "tsunade": {
    "ninjutsu": 5,
    "taijutsu": 5,
    "genjutsu": 3.5,
    "intelligence": 5,
    "strength": 5,
    "speed": 3.5,
    "stamina": 4,
    "hand_seals": 4,
    "total": 35,
    "notes": "Scared of blood, insanely powerful, Sakura didn't inherit her true abilities"
  },
  "hinata": {
    "ninjutsu": 3,
    "taijutsu": 3.5,
    "genjutsu": 2.5,
    "intelligence": 3.5,
    "strength": 1.5,
    "speed": 2.5,
    "stamina": 2,
    "hand_seals": 3,
    "total": "21.5",
    "notes": "Legend. Doesn't have more points than Sakura but still way better"
  },
  "ino": {
    "ninjutsu": 3.5,
    "taijutsu": 1.5,
    "genjutsu": 3,
    "intelligence": 3,
    "strength": 2.5,
    "speed": 2.5,
    "stamina": 2.5,
    "hand_seals": 2.5,
    "total": 21,
    "notes": "Better than Sakura, doesn't have an enormous forehead, can do interesting Jutsu's"
  }
}
